spark_connect_proxy/__init__.py
spark_connect_proxy/config.py
spark_connect_proxy/logger.py
spark_connect_proxy/security.py
spark_connect_proxy/server.py
spark_connect_proxy/client_examples/ibis_client_example.py
spark_connect_proxy/utilities/create_jwt.py
spark_connect_proxy/utilities/tls_utilities.py
spark_connect_proxy-0.0.14.dist-info/licenses/LICENSE
spark_connect_proxy-0.0.14.dist-info/METADATA
spark_connect_proxy-0.0.14.dist-info/WHEEL
spark_connect_proxy-0.0.14.dist-info/entry_points.txt
spark_connect_proxy-0.0.14.dist-info/top_level.txt
spark_connect_proxy-0.0.14.dist-info/RECORD
