Metadata-Version: 2.4
Name: spark-connect-proxy
Version: 0.0.14
Summary: A reverse proxy server which allows secure connectivity to a Spark Connect server
Author-email: Philip Moore <philip@gizmodata.com>
License-Expression: Apache-2.0
Project-URL: Homepage, https://github.com/gizmodata/spark-connect-proxy
Keywords: spark,pyspark,grpc,reverse-proxy,connect,spark-connect
Classifier: Programming Language :: Python
Classifier: Programming Language :: Python :: 3
Requires-Python: >=3.9
License-File: LICENSE
Requires-Dist: click==8.1.*
Requires-Dist: pyspark==3.5.1
Requires-Dist: grpcio-tools==1.66.*
Requires-Dist: grpcio-channelz==1.66.*
Requires-Dist: grpcio-status==1.66.*
Requires-Dist: pyjwt==2.9.*
Requires-Dist: python-dotenv==1.1.*
Requires-Dist: pyarrow_hotfix==0.6.*
Requires-Dist: protobuf==5.27.2
Requires-Dist: pyOpenSSL==24.2.1
Provides-Extra: dev
Requires-Dist: bumpver; extra == "dev"
Requires-Dist: pip-tools; extra == "dev"
Requires-Dist: pytest; extra == "dev"
Provides-Extra: client
Requires-Dist: ibis-framework==9.5.*; extra == "client"
Requires-Dist: codetiming==1.4.*; extra == "client"
Requires-Dist: pandas==2.2.*; extra == "client"
Requires-Dist: pyarrow==17.0.*; extra == "client"
Dynamic: license-file
